icap_commons/__init__.py
icap_commons/gcp.py
icap_commons/pubsub.py
icap_commons-0.4.0.dist-info/METADATA
icap_commons-0.4.0.dist-info/WHEEL
icap_commons-0.4.0.dist-info/top_level.txt
icap_commons-0.4.0.dist-info/RECORD
