Metadata-Version: 2.1
Name: icap-commons
Version: 0.4.0
Summary: Example Python library
Author: Makrand Bhonde
Author-email: makrand.bhonde@bluealtair.com
Classifier: Development Status :: 3 - Alpha
Classifier: Intended Audience :: Developers
Classifier: License :: OSI Approved :: MIT License
Classifier: Programming Language :: Python :: 3
Classifier: Programming Language :: Python :: 3.6
Classifier: Programming Language :: Python :: 3.7
Classifier: Programming Language :: Python :: 3.8
Classifier: Programming Language :: Python :: 3.9
